faculty_cli/__init__.py
faculty_cli/cli.py
faculty_cli/parse.py
faculty_cli/shell.py
faculty_cli/update.py
faculty_cli/version.py
faculty_cli-0.15.0.dist-info/licenses/LICENSE-2.0.txt
test/__init__.py
test/conftest.py
test/fixtures.py
test/test_datasets.py
test/test_parse.py
test/test_projects.py
test/test_servers.py
faculty_cli-0.15.0.dist-info/METADATA
faculty_cli-0.15.0.dist-info/WHEEL
faculty_cli-0.15.0.dist-info/entry_points.txt
faculty_cli-0.15.0.dist-info/top_level.txt
faculty_cli-0.15.0.dist-info/RECORD
